RISC_CPU.srcs/sources_1/new/define.v
// -------------------------------------------------------------------------
// Project: Thiet ke RISC CPU don gian
// Khoa Khoa hoc va Ky thuat May tinh - HCMUT
// -------------------------------------------------------------------------
// Mục đích tạo file này: Tăng tính thống nhất, dễ dàng chỉnh sửa
//Cách dùng : Import source vào vivado, click chuột phải chọn Set Global Include 
`ifndef DEFINES_VH
`define DEFINES_VH

// 1. THÔNG SỐ ĐỘ RỘNG (Parameters)
`define DATA_WIDTH    32    // Do rong du lieu mac dinh
`define ADDR_WIDTH    32    // Do rong dia chi (Memory/Mux)
`define OPCODE_WIDTH  3     // 3-bit opcode
`define ADDR_SPACE    32    // 32 khong gian dia chi

// 2. MÃ OPCODE (ALU Operations)
`define HLT 3'b000   // Dung hoat dong chuong trinh
`define SKZ 3'b001   // Kiem tra zero, bo qua lenh tiep theo
`define ADD 3'b010   // Cong Accumulator voi bo nho
`define AND 3'b011   // Phep toan AND logic
`define XOR 3'b100   // Phep toan XOR logic
`define LDA 3'b101   // Doc gia tri tu bo nho vao Accumulator
`define STO 3'b110   // Ghi du lieu Accumulator vao bo nho
`define JMP 3'b111   // Lenh nhay khong dieu kien

// 3. CÁC TRẠNG THÁI CỦA BỘ ĐIỀU KHIỂN (Controller States)
// Gom 8 trang thai hoat dong lien tuc
`define INST_ADDR  3'b000
`define INST_FETCH 3'b001
`define INST_LOAD  3'b010
`define IDLE       3'b011
`define OP_ADDR    3'b100
`define OP_FETCH   3'b101
`define ALU_OP     3'b110
`define STORE      3'b111

// 4. CÁC TÍN HIỆU ĐIỀU KHIỂN (Control Signals Logic)[cite: 1]
`define READ_MEM  1'b1
`define WRITE_MEM 1'b1
`define SEL_PC    1'b1
`define SEL_IR    1'b0

`endif // DEFINES_VH

RISC_CPU.srcs/sources_1/new/address_mux.v
`timescale 1ns / 1ps
//////////////////////////////////////////////////////////////////////////////////
// Company: 
// Engineer: 
// 
// Create Date: 05/06/2026 10:17:34 PM
// Design Name: 
// Module Name: address_mux
// Project Name: 
// Target Devices: 
// Tool Versions: 
// Description: 
// 
// Dependencies: 
// 
// Revision:
// Revision 0.01 - File Created
// Additional Comments:
// 
//////////////////////////////////////////////////////////////////////////////////

`include "define.v"
module address_mux(
    input wire sel,                             
    input wire [`ADDR_WIDTH-1:0] pc_addr,       
    input wire [`ADDR_WIDTH-1:0] ir_addr,   
    output wire [`ADDR_WIDTH-1:0] mem_addr
    );
    assign mem_addr = (sel == `SEL_PC) ? pc_addr : ir_addr;
endmodule

RISC_CPU.srcs/sim_1/new/address_mux_tb.v
`timescale 1ns / 1ps
`include "define.v"

module address_mux_tb;
    reg sel;
    reg  [`ADDR_WIDTH-1:0] pc_addr;
    reg  [`ADDR_WIDTH-1:0] ir_addr;
    wire [`ADDR_WIDTH-1:0] mem_addr;

    // ── DUT ──────────────────────────────────────────────────────────
    address_mux dut (
        .sel(sel),
        .pc_addr(pc_addr),
        .ir_addr(ir_addr),
        .mem_addr(mem_addr)
    );

    // ── Task tự động kiểm tra ────────────────────────────────────────
    integer pass_count = 0;
    integer fail_count = 0;

    task check_output;
        input [`ADDR_WIDTH-1:0] expected;
        input [63:0]            test_num;
        begin
            #1; // Cho tín hiệu ổn định
            if (mem_addr === expected) begin
                $display("PASS [Test %0d] sel=%b | pc=%h | ir=%h => mem_addr=%h",
                          test_num, sel, pc_addr, ir_addr, mem_addr);
                pass_count = pass_count + 1;
            end else begin
                $display("FAIL [Test %0d] sel=%b | pc=%h | ir=%h => mem_addr=%h (expected %h)",
                          test_num, sel, pc_addr, ir_addr, mem_addr, expected);
                fail_count = fail_count + 1;
            end
        end
    endtask

    // ── Waveform dump ─────────────────────────────────────────────────
    initial begin
        $dumpfile("address_mux_tb.vcd");
        $dumpvars(0, address_mux_tb);
    end

    // ── Stimulus ──────────────────────────────────────────────────────
    initial begin
        $display("=== Bat dau mo phong Address MUX ===");

        // Giá trị mặc định
        sel     = `SEL_IR;
        pc_addr = 32'h00000010;
        ir_addr = 32'h000000FF;
        #10;

        // Test 1: SEL_IR → phải ra ir_addr
        sel = `SEL_IR;
        check_output(ir_addr, 1);

        // Test 2: SEL_PC → phải ra pc_addr
        #10; sel = `SEL_PC;
        check_output(pc_addr, 2);

        // Test 3: PC thay đổi trong khi sel = SEL_PC
        #10; pc_addr = 32'h00000011;
        check_output(32'h00000011, 3);

        // Test 4: Quay lại SEL_IR
        #10; sel = `SEL_IR;
        check_output(ir_addr, 4);

        // Test 5: ir_addr thay đổi trong khi sel = SEL_IR
        #10; ir_addr = 32'hDEADBEEF;
        check_output(32'hDEADBEEF, 5);

        // Test 6: Edge case - địa chỉ 0
        #10;
        pc_addr = 32'h00000000;
        ir_addr = 32'h00000000;
        sel = `SEL_PC;
        check_output(32'h00000000, 6);

        // Test 7: Edge case - địa chỉ max
        #10;
        pc_addr = 32'hFFFFFFFF;
        ir_addr = 32'hFFFFFFFF;
        sel = `SEL_IR;
        check_output(32'hFFFFFFFF, 7);

        // Test 8: Tất cả bit xen kẽ
        #10;
        pc_addr = 32'hAAAAAAAA;
        ir_addr = 32'h55555555;
        sel = `SEL_PC;
        check_output(32'hAAAAAAAA, 8);
        #10; sel = `SEL_IR;
        check_output(32'h55555555, 9);

        // ── Tổng kết ──────────────────────────────────────────────────
        #10;
        $display("=== KET QUA: %0d PASS | %0d FAIL ===", pass_count, fail_count);
        if (fail_count == 0)
            $display(">>> PASS TOAN BO TEST CASES <<<");
        else
            $display(">>> CO %0d LOI CAN KIEM TRA LAI <<<", fail_count);
        $finish;
    end
endmodule

RISC_CPU.sim/sim_1/behav/xsim/address_mux_tb.vcd
$date
   Thu May 14 20:12:18 2026
$end

$version
  2025.2
  $dumpfile ("address_mux_tb.vcd") 
$end

$timescale
  1ps
$end

$scope module address_mux_tb $end
$var reg 1 ! sel $end
$var reg 32 " pc_addr [31:0] $end
$var reg 32 # ir_addr [31:0] $end
$var wire 32 $ mem_addr [31:0] $end
$var integer 32 % pass_count [31:0] $end
$var integer 32 & fail_count [31:0] $end
$scope module dut $end
$var wire 1 ' sel $end
$var wire 32 ( pc_addr [31:0] $end
$var wire 32 ) ir_addr [31:0] $end
$var wire 32 $ mem_addr [31:0] $end
$upscope $end
$scope task check_output $end
$var reg 32 * expected [31:0] $end
$var reg 64 + test_num [63:0] $end
$upscope $end
$upscope $end
$enddefinitions $end

#0
$dumpvars
0!
b10000 "
b11111111 #
b11111111 $
b0 %
b0 &
0'
b10000 (
b11111111 )
bx *
bx +
$end

#10000
b11111111 *
b1 +

#11000
b1 %

#21000
1!
b10000 $
1'
b10000 *
b10 +

#22000
b10 %

#32000
b10001 "
b10001 $
b10001 (
b10001 *
b11 +

#33000
b11 %

#43000
0!
b11111111 $
0'
b11111111 *
b100 +

#44000
b100 %

#54000
b11011110101011011011111011101111 #
b11011110101011011011111011101111 $
b11011110101011011011111011101111 )
b11011110101011011011111011101111 *
b101 +

#55000
b101 %

#65000
1!
b0 "
b0 #
b0 $
1'
b0 (
b0 )
b0 *
b110 +

#66000
b110 %

#76000
0!
b11111111111111111111111111111111 "
b11111111111111111111111111111111 #
b11111111111111111111111111111111 $
0'
b11111111111111111111111111111111 (
b11111111111111111111111111111111 )
b11111111111111111111111111111111 *
b111 +

#77000
b111 %

#87000
1!
b10101010101010101010101010101010 "
b1010101010101010101010101010101 #
b10101010101010101010101010101010 $
1'
b10101010101010101010101010101010 (
b1010101010101010101010101010101 )
b10101010101010101010101010101010 *
b1000 +

#88000
b1000 %

#98000
0!
b1010101010101010101010101010101 $
0'
b1010101010101010101010101010101 *
b1001 +

#99000
b1001 %
